{
  "keynote_1": {
    "tag": "Keynote #1",
    "time": "11:10~11:40",
    "duration": "30min",
    "title" : "キーノートトーク #1タイトルサンプル",
    "speakers": [
      "session1_1",
      "session1_2",
      "session1_3",
      "session1_4"
    ],
    "description": "これはキーノートトーク #1の説明文のサンプルです。これはキーノートトーク #1の説明文のサンプルです。これはキーノートトーク #1の説明文のサンプルです。"
  },
  "keynote_2": {
    "tag": "Keynote #2",
    "time": "11:10~11:40",
    "duration": "30min",
    "title" : "キーノートトーク #2タイトルサンプル",
    "speakers": [
      "session2_1",
      "session2_2"
    ],
    "description": "これはキーノートトーク #1の説明文のサンプルです。これはキーノートトーク #1の説明文のサンプルです。これはキーノートトーク #1の説明文のサンプルです。"
  },
  "talk_1": {
    "tag": "talk #1",
    "time": "11:10~11:40",
    "duration": "30min",
    "title" : "キーノートトーク #1タイトルサンプル",
    "speakers": [
      "session3_1"
    ],
    "description": "これはキーノートトーク #1の説明文のサンプルです。これはキーノートトーク #1の説明文のサンプルです。これはキーノートトーク #1の説明文のサンプルです。"
  },
  "talk_2": {
    "tag": "talk #2",
    "time": "11:10~11:40",
    "duration": "30min",
    "title" : "キーノートトーク #1タイトルサンプル",
    "speakers": [
      "session1_1",
      "session2_1"
    ],
    "description": "これはキーノートトーク #1の説明文のサンプルです。これはキーノートトーク #1の説明文のサンプルです。これはキーノートトーク #1の説明文のサンプルです。"
  },
  "talk_3": {
    "tag": "talk #3",
    "time": "11:10~11:40",
    "duration": "30min",
    "title" : "キーノートトーク #1タイトルサンプル",
    "speakers": [
      "session1_1",
      "session2_1"
    ],
    "description": "これはキーノートトーク #1の説明文のサンプルです。これはキーノートトーク #1の説明文のサンプルです。これはキーノートトーク #1の説明文のサンプルです。"
  },
  "talk_4": {
    "tag": "talk #4",
    "time": "11:10~11:40",
    "duration": "30min",
    "title" : "キーノートトーク #1タイトルサンプル",
    "speakers": [
      "session1_1",
      "session2_1"
    ],
    "description": "これはキーノートトーク #1の説明文のサンプルです。これはキーノートトーク #1の説明文のサンプルです。これはキーノートトーク #1の説明文のサンプルです。"
  },
  "talk_5": {
    "tag": "talk #5",
    "time": "11:10~11:40",
    "duration": "30min",
    "title" : "キーノートトーク #1タイトルサンプル",
    "speakers": [
      "session1_1",
      "session2_1"
    ],
    "description": "これはキーノートトーク #1の説明文のサンプルです。これはキーノートトーク #1の説明文のサンプルです。これはキーノートトーク #1の説明文のサンプルです。"
  }
}